{
  "UserAgent": "MobileHub/1.0",
  "Version": "1.0",
  "CredentialsProvider": {
    "CognitoIdentity": {
      "Default": {
        "PoolId": "us-east-1:3d04c1c6-d44b-4211-893b-a625769079e9",
        "Region": "us-east-1"
      }
    }
  },
  "IdentityManager": {
    "Default": {}
  },
  "PinpointAnalytics": {
    "Default": {
      "AppId": "4d2e0c54d1774849a58db08ad40d6f47",
      "Region": "us-east-1"
    }
  },
  "PinpointTargeting": {
    "Default": {
      "Region": "us-east-1"
    }
  }
}